{
  "id": "table",
  "name": "Table",
  "totalProps": 0,
  "packageName": "@nimbus-ds/table",
  "version": "2.0.0",
  "docLink": "https://nimbus.nuvemshop.com.br/documentation/composite-components/table",
  "props": [],
  "subComponents": [
    {
      "name": "Table.Body",
      "totalProps": 0,
      "props": []
    },
    {
      "name": "Table.Cell",
      "totalProps": 0,
      "props": []
    },
    {
      "name": "Table.Head",
      "totalProps": 0,
      "props": []
    },
    {
      "name": "Table.Row",
      "totalProps": 0,
      "props": []
    }
  ]
}